<?xml version="1.0" encoding="utf-8" ?>
<c2layout>
    <name>stageView</name>
    <sid>9603615945991896</sid>
    <event-sheet>stageView</event-sheet>
    <size>
        <width>1280</width>
        <height>720</height>
    </size>
    <margins>
        <horizontal>500</horizontal>
        <vertical>500</vertical>
    </margins>
    <unbounded-scrolling>1</unbounded-scrolling>
    <layers>
        <layer name="bg" sid="458844855612229">
            <initially-visible>1</initially-visible>
            <background-color>255,255,255</background-color>
            <transparent>0</transparent>
            <parallax>
                <x>1</x>
                <y>1</y>
            </parallax>
            <zoom-rate>1</zoom-rate>
            <opacity>1</opacity>
            <force-own-texture>0</force-own-texture>
            <global>0</global>
            <use-render-cells>0</use-render-cells>
            <blend-mode>0</blend-mode>
            <effect-fallback>0</effect-fallback>
            <instances>
                <instance type="stageMapChap" uid="45">
                    <properties>
                        <initial-visibility>Visible</initial-visibility>
                        <initial-animation>Default</initial-animation>
                        <initial-frame>0</initial-frame>
                        <collisions>Enabled</collisions>
                    </properties>
                    <behavior-instances>
                        <behavior-instance type="DragDrop">
                            <properties>
                                <axes>Horizontal only</axes>
                                <initial-state>Disabled</initial-state>
                            </properties>
                        </behavior-instance>
                        <behavior-instance type="MoveTo">
                            <properties>
                                <activated>No</activated>
                                <max-speed>2000</max-speed>
                                <acceleration>0</acceleration>
                                <deceleration>0</deceleration>
                            </properties>
                        </behavior-instance>
                    </behavior-instances>
                    <blend-mode>0</blend-mode>
                    <effect-fallback>0</effect-fallback>
                    <world>
                        <x>640</x>
                        <y>360</y>
                        <z>0</z>
                        <width>1280</width>
                        <height>1280</height>
                        <depth>0</depth>
                        <hotspotX>0.5</hotspotX>
                        <hotspotY>0.5</hotspotY>
                        <angle>0</angle>
                        <opacity>1</opacity>
                    </world>
                </instance>
                <instance type="focus" uid="125">
                    <properties>
                        <initial-visibility>Visible</initial-visibility>
                        <initial-animation>Default</initial-animation>
                        <initial-frame>0</initial-frame>
                        <collisions>Enabled</collisions>
                    </properties>
                    <behavior-instances>
                        <behavior-instance type="ScrollTo">
                            <properties>
                                <initial-state>Enabled</initial-state>
                            </properties>
                        </behavior-instance>
                    </behavior-instances>
                    <blend-mode>0</blend-mode>
                    <effect-fallback>0</effect-fallback>
                    <world>
                        <x>640</x>
                        <y>360</y>
                        <z>0</z>
                        <width>4</width>
                        <height>4</height>
                        <depth>0</depth>
                        <hotspotX>0.5</hotspotX>
                        <hotspotY>0.5</hotspotY>
                        <angle>0</angle>
                        <opacity>1</opacity>
                    </world>
                </instance>
            </instances>
            <effects />
        </layer>
        <layer name="effect" sid="6841473502249313">
            <initially-visible>1</initially-visible>
            <background-color>255,255,255</background-color>
            <transparent>1</transparent>
            <parallax>
                <x>1</x>
                <y>1</y>
            </parallax>
            <zoom-rate>1</zoom-rate>
            <opacity>1</opacity>
            <force-own-texture>0</force-own-texture>
            <global>0</global>
            <use-render-cells>0</use-render-cells>
            <blend-mode>0</blend-mode>
            <effect-fallback>0</effect-fallback>
            <instances />
            <effects />
        </layer>
        <layer name="hud" sid="1114454397788011">
            <initially-visible>1</initially-visible>
            <background-color>255,255,255</background-color>
            <transparent>1</transparent>
            <parallax>
                <x>0</x>
                <y>0</y>
            </parallax>
            <zoom-rate>1</zoom-rate>
            <opacity>1</opacity>
            <force-own-texture>0</force-own-texture>
            <global>0</global>
            <use-render-cells>0</use-render-cells>
            <blend-mode>0</blend-mode>
            <effect-fallback>0</effect-fallback>
            <instances>
                <instance type="menuButtonPackage" uid="44">
                    <properties>
                        <initial-visibility>Visible</initial-visibility>
                        <initial-animation>Close</initial-animation>
                        <initial-frame>0</initial-frame>
                        <collisions>Enabled</collisions>
                    </properties>
                    <instance-variables>
                        <ready>false</ready>
                    </instance-variables>
                    <behavior-instances>
                        <behavior-instance type="Anchor">
                            <properties>
                                <left-edge>None</left-edge>
                                <top-edge>Window bottom</top-edge>
                                <right-edge>None</right-edge>
                                <bottom-edge>None</bottom-edge>
                                <initial-state>Enabled</initial-state>
                            </properties>
                        </behavior-instance>
                    </behavior-instances>
                    <blend-mode>0</blend-mode>
                    <effect-fallback>0</effect-fallback>
                    <world>
                        <x>90</x>
                        <y>640</y>
                        <z>0</z>
                        <width>155</width>
                        <height>168</height>
                        <depth>0</depth>
                        <hotspotX>0.503225803</hotspotX>
                        <hotspotY>0.5</hotspotY>
                        <angle>0</angle>
                        <opacity>1</opacity>
                    </world>
                </instance>
                <instance type="stageSummary" uid="48">
                    <properties>
                        <initial-visibility>Visible</initial-visibility>
                        <initial-animation>Default</initial-animation>
                        <initial-frame>0</initial-frame>
                        <collisions>Enabled</collisions>
                    </properties>
                    <behavior-instances>
                        <behavior-instance type="Anchor">
                            <properties>
                                <left-edge>None</left-edge>
                                <top-edge>Window bottom</top-edge>
                                <right-edge>None</right-edge>
                                <bottom-edge>None</bottom-edge>
                                <initial-state>Enabled</initial-state>
                            </properties>
                        </behavior-instance>
                    </behavior-instances>
                    <blend-mode>0</blend-mode>
                    <effect-fallback>0</effect-fallback>
                    <world>
                        <x>710</x>
                        <y>640</y>
                        <z>0</z>
                        <width>1100</width>
                        <height>135</height>
                        <depth>0</depth>
                        <hotspotX>0.500518143</hotspotX>
                        <hotspotY>0.503703713</hotspotY>
                        <angle>0</angle>
                        <opacity>1</opacity>
                    </world>
                </instance>
                <instance type="stageInfoText" uid="50">
                    <properties>
                        <text>안녕하세요</text>
                        <initial-visibility>Visible</initial-visibility>
                        <font>배달의민족 주아,-29,700,0</font>
                        <color>0,0,0</color>
                        <horizontal-alignment>Left</horizontal-alignment>
                        <vertical-alignment>Top</vertical-alignment>
                        <hotspot>Center</hotspot>
                        <wrapping>Word</wrapping>
                        <line-height>0</line-height>
                    </properties>
                    <behavior-instances>
                        <behavior-instance type="Anchor">
                            <properties>
                                <left-edge>None</left-edge>
                                <top-edge>Window bottom</top-edge>
                                <right-edge>None</right-edge>
                                <bottom-edge>None</bottom-edge>
                                <initial-state>Enabled</initial-state>
                            </properties>
                        </behavior-instance>
                    </behavior-instances>
                    <blend-mode>0</blend-mode>
                    <effect-fallback>0</effect-fallback>
                    <world>
                        <x>710</x>
                        <y>653</y>
                        <z>0</z>
                        <width>1030</width>
                        <height>121</height>
                        <depth>0</depth>
                        <hotspotX>0.5</hotspotX>
                        <hotspotY>0.5</hotspotY>
                        <angle>0</angle>
                        <opacity>1</opacity>
                    </world>
                </instance>
                <instance type="henCage" uid="133">
                    <properties>
                        <initial-visibility>Visible</initial-visibility>
                        <initial-animation>Default</initial-animation>
                        <initial-frame>0</initial-frame>
                        <collisions>Enabled</collisions>
                    </properties>
                    <instance-variables>
                        <id>0</id>
                        <kind></kind>
                        <type></type>
                        <bonus>0</bonus>
                    </instance-variables>
                    <behavior-instances>
                        <behavior-instance type="Anchor">
                            <properties>
                                <left-edge>None</left-edge>
                                <top-edge>Window bottom</top-edge>
                                <right-edge>None</right-edge>
                                <bottom-edge>None</bottom-edge>
                                <initial-state>Disabled</initial-state>
                            </properties>
                        </behavior-instance>
                        <behavior-instance type="Sine">
                            <properties>
                                <active-on-start>No</active-on-start>
                                <movement>Angle</movement>
                                <wave>Sine</wave>
                                <period>10</period>
                                <period-random>1</period-random>
                                <period-offset>0</period-offset>
                                <period-offset-random>10</period-offset-random>
                                <magnitude>5</magnitude>
                                <magnitude-random>1</magnitude-random>
                            </properties>
                        </behavior-instance>
                        <behavior-instance type="PinToImagePoint" />
                    </behavior-instances>
                    <blend-mode>0</blend-mode>
                    <effect-fallback>0</effect-fallback>
                    <world>
                        <x>992</x>
                        <y>93</y>
                        <z>0</z>
                        <width>80</width>
                        <height>82</height>
                        <depth>0</depth>
                        <hotspotX>0.5</hotspotX>
                        <hotspotY>1</hotspotY>
                        <angle>0</angle>
                        <opacity>1</opacity>
                    </world>
                </instance>
                <instance type="henCage" uid="134">
                    <properties>
                        <initial-visibility>Visible</initial-visibility>
                        <initial-animation>Default</initial-animation>
                        <initial-frame>0</initial-frame>
                        <collisions>Enabled</collisions>
                    </properties>
                    <instance-variables>
                        <id>0</id>
                        <kind></kind>
                        <type></type>
                        <bonus>0</bonus>
                    </instance-variables>
                    <behavior-instances>
                        <behavior-instance type="Anchor">
                            <properties>
                                <left-edge>None</left-edge>
                                <top-edge>Window bottom</top-edge>
                                <right-edge>None</right-edge>
                                <bottom-edge>None</bottom-edge>
                                <initial-state>Disabled</initial-state>
                            </properties>
                        </behavior-instance>
                        <behavior-instance type="Sine">
                            <properties>
                                <active-on-start>No</active-on-start>
                                <movement>Angle</movement>
                                <wave>Sine</wave>
                                <period>10</period>
                                <period-random>1</period-random>
                                <period-offset>0</period-offset>
                                <period-offset-random>10</period-offset-random>
                                <magnitude>5</magnitude>
                                <magnitude-random>1</magnitude-random>
                            </properties>
                        </behavior-instance>
                        <behavior-instance type="PinToImagePoint" />
                    </behavior-instances>
                    <blend-mode>0</blend-mode>
                    <effect-fallback>0</effect-fallback>
                    <world>
                        <x>1102</x>
                        <y>115</y>
                        <z>0</z>
                        <width>80</width>
                        <height>82</height>
                        <depth>0</depth>
                        <hotspotX>0.5</hotspotX>
                        <hotspotY>1</hotspotY>
                        <angle>0</angle>
                        <opacity>1</opacity>
                    </world>
                </instance>
                <instance type="henCage" uid="135">
                    <properties>
                        <initial-visibility>Visible</initial-visibility>
                        <initial-animation>Default</initial-animation>
                        <initial-frame>0</initial-frame>
                        <collisions>Enabled</collisions>
                    </properties>
                    <instance-variables>
                        <id>0</id>
                        <kind></kind>
                        <type></type>
                        <bonus>0</bonus>
                    </instance-variables>
                    <behavior-instances>
                        <behavior-instance type="Anchor">
                            <properties>
                                <left-edge>None</left-edge>
                                <top-edge>Window bottom</top-edge>
                                <right-edge>None</right-edge>
                                <bottom-edge>None</bottom-edge>
                                <initial-state>Disabled</initial-state>
                            </properties>
                        </behavior-instance>
                        <behavior-instance type="Sine">
                            <properties>
                                <active-on-start>No</active-on-start>
                                <movement>Angle</movement>
                                <wave>Sine</wave>
                                <period>10</period>
                                <period-random>1</period-random>
                                <period-offset>0</period-offset>
                                <period-offset-random>10</period-offset-random>
                                <magnitude>5</magnitude>
                                <magnitude-random>1</magnitude-random>
                            </properties>
                        </behavior-instance>
                        <behavior-instance type="PinToImagePoint" />
                    </behavior-instances>
                    <blend-mode>0</blend-mode>
                    <effect-fallback>0</effect-fallback>
                    <world>
                        <x>1218</x>
                        <y>128</y>
                        <z>0</z>
                        <width>80</width>
                        <height>82</height>
                        <depth>0</depth>
                        <hotspotX>0.5</hotspotX>
                        <hotspotY>1</hotspotY>
                        <angle>0</angle>
                        <opacity>1</opacity>
                    </world>
                </instance>
                <instance type="heart" uid="160">
                    <properties>
                        <initial-visibility>Visible</initial-visibility>
                        <initial-animation>Default</initial-animation>
                        <initial-frame>0</initial-frame>
                        <collisions>Enabled</collisions>
                    </properties>
                    <behavior-instances>
                        <behavior-instance type="Anchor">
                            <properties>
                                <left-edge>None</left-edge>
                                <top-edge>Window bottom</top-edge>
                                <right-edge>None</right-edge>
                                <bottom-edge>None</bottom-edge>
                                <initial-state>Enabled</initial-state>
                            </properties>
                        </behavior-instance>
                    </behavior-instances>
                    <blend-mode>0</blend-mode>
                    <effect-fallback>0</effect-fallback>
                    <world>
                        <x>1135</x>
                        <y>510</y>
                        <z>0</z>
                        <width>214.102783203</width>
                        <height>42.820556641</height>
                        <depth>0</depth>
                        <hotspotX>0.5</hotspotX>
                        <hotspotY>0.5</hotspotY>
                        <angle>0</angle>
                        <opacity>1</opacity>
                    </world>
                </instance>
                <instance type="heartTimer" uid="161">
                    <properties>
                        <text>00:00</text>
                        <initial-visibility>Visible</initial-visibility>
                        <font>배달의민족 주아,-29,700,0</font>
                        <color>0,0,0</color>
                        <horizontal-alignment>Right</horizontal-alignment>
                        <vertical-alignment>Center</vertical-alignment>
                        <hotspot>Right</hotspot>
                        <wrapping>Word</wrapping>
                        <line-height>0</line-height>
                    </properties>
                    <behavior-instances>
                        <behavior-instance type="Anchor">
                            <properties>
                                <left-edge>None</left-edge>
                                <top-edge>Window bottom</top-edge>
                                <right-edge>None</right-edge>
                                <bottom-edge>None</bottom-edge>
                                <initial-state>Enabled</initial-state>
                            </properties>
                        </behavior-instance>
                    </behavior-instances>
                    <blend-mode>0</blend-mode>
                    <effect-fallback>0</effect-fallback>
                    <world>
                        <x>1235</x>
                        <y>555</y>
                        <z>0</z>
                        <width>453</width>
                        <height>49</height>
                        <depth>0</depth>
                        <hotspotX>1</hotspotX>
                        <hotspotY>0.5</hotspotY>
                        <angle>0</angle>
                        <opacity>1</opacity>
                    </world>
                </instance>
                <instance type="skyLeftCover" uid="51">
                    <properties>
                        <initial-visibility>Visible</initial-visibility>
                        <initial-animation>Default</initial-animation>
                        <initial-frame>0</initial-frame>
                        <collisions>Enabled</collisions>
                    </properties>
                    <behavior-instances>
                        <behavior-instance type="PinToImagePoint" />
                        <behavior-instance type="MoveTo">
                            <properties>
                                <activated>Yes</activated>
                                <max-speed>2000</max-speed>
                                <acceleration>0</acceleration>
                                <deceleration>0</deceleration>
                            </properties>
                        </behavior-instance>
                        <behavior-instance type="Sine">
                            <properties>
                                <active-on-start>Yes</active-on-start>
                                <movement>Size</movement>
                                <wave>Sine</wave>
                                <period>2.4</period>
                                <period-random>0</period-random>
                                <period-offset>0</period-offset>
                                <period-offset-random>0</period-offset-random>
                                <magnitude>15</magnitude>
                                <magnitude-random>0</magnitude-random>
                            </properties>
                        </behavior-instance>
                    </behavior-instances>
                    <blend-mode>0</blend-mode>
                    <effect-fallback>0</effect-fallback>
                    <world>
                        <x>-640</x>
                        <y>360</y>
                        <z>0</z>
                        <width>1421.875</width>
                        <height>1421.875</height>
                        <depth>0</depth>
                        <hotspotX>0.521428585</hotspotX>
                        <hotspotY>0.5</hotspotY>
                        <angle>0</angle>
                        <opacity>1</opacity>
                    </world>
                </instance>
                <instance type="skyRightCover" uid="52">
                    <properties>
                        <initial-visibility>Visible</initial-visibility>
                        <initial-animation>Default</initial-animation>
                        <initial-frame>0</initial-frame>
                        <collisions>Enabled</collisions>
                    </properties>
                    <behavior-instances>
                        <behavior-instance type="PinToImagePoint" />
                        <behavior-instance type="MoveTo">
                            <properties>
                                <activated>Yes</activated>
                                <max-speed>2000</max-speed>
                                <acceleration>0</acceleration>
                                <deceleration>0</deceleration>
                            </properties>
                        </behavior-instance>
                        <behavior-instance type="Sine">
                            <properties>
                                <active-on-start>Yes</active-on-start>
                                <movement>Size</movement>
                                <wave>Sine</wave>
                                <period>2.4</period>
                                <period-random>0</period-random>
                                <period-offset>0</period-offset>
                                <period-offset-random>0</period-offset-random>
                                <magnitude>15</magnitude>
                                <magnitude-random>0</magnitude-random>
                            </properties>
                        </behavior-instance>
                    </behavior-instances>
                    <blend-mode>0</blend-mode>
                    <effect-fallback>0</effect-fallback>
                    <world>
                        <x>1920</x>
                        <y>360</y>
                        <z>0</z>
                        <width>1421.875</width>
                        <height>1421.875</height>
                        <depth>0</depth>
                        <hotspotX>0.478571415</hotspotX>
                        <hotspotY>0.5</hotspotY>
                        <angle>0</angle>
                        <opacity>1</opacity>
                    </world>
                </instance>
                <instance type="stageViewTransparentCover" uid="83">
                    <properties>
                        <initial-visibility>Visible</initial-visibility>
                        <initial-animation>Default</initial-animation>
                        <initial-frame>0</initial-frame>
                        <collisions>Enabled</collisions>
                    </properties>
                    <behavior-instances>
                        <behavior-instance type="DragDrop">
                            <properties>
                                <axes>Horizontal only</axes>
                                <initial-state>Enabled</initial-state>
                            </properties>
                        </behavior-instance>
                        <behavior-instance type="MoveTo">
                            <properties>
                                <activated>Yes</activated>
                                <max-speed>2000</max-speed>
                                <acceleration>0</acceleration>
                                <deceleration>0</deceleration>
                            </properties>
                        </behavior-instance>
                    </behavior-instances>
                    <blend-mode>0</blend-mode>
                    <effect-fallback>0</effect-fallback>
                    <world>
                        <x>640</x>
                        <y>1500</y>
                        <z>0</z>
                        <width>1280</width>
                        <height>1280</height>
                        <depth>0</depth>
                        <hotspotX>0.5</hotspotX>
                        <hotspotY>0.5</hotspotY>
                        <angle>0</angle>
                        <opacity>1</opacity>
                    </world>
                </instance>
                <instance type="stageStartButton" uid="122">
                    <properties>
                        <initial-visibility>Visible</initial-visibility>
                        <initial-animation>Default</initial-animation>
                        <initial-frame>0</initial-frame>
                        <collisions>Enabled</collisions>
                    </properties>
                    <instance-variables>
                        <On>false</On>
                    </instance-variables>
                    <behavior-instances>
                        <behavior-instance type="Anchor">
                            <properties>
                                <left-edge>None</left-edge>
                                <top-edge>Window bottom</top-edge>
                                <right-edge>None</right-edge>
                                <bottom-edge>None</bottom-edge>
                                <initial-state>Enabled</initial-state>
                            </properties>
                        </behavior-instance>
                    </behavior-instances>
                    <blend-mode>0</blend-mode>
                    <effect-fallback>0</effect-fallback>
                    <world>
                        <x>1125</x>
                        <y>640</y>
                        <z>0</z>
                        <width>180</width>
                        <height>100</height>
                        <depth>0</depth>
                        <hotspotX>0.5</hotspotX>
                        <hotspotY>0.5</hotspotY>
                        <angle>0</angle>
                        <opacity>1</opacity>
                    </world>
                </instance>
            </instances>
            <effects />
        </layer>
        <layer name="fade" sid="509672822618823">
            <initially-visible>1</initially-visible>
            <background-color>255,255,255</background-color>
            <transparent>1</transparent>
            <parallax>
                <x>0</x>
                <y>0</y>
            </parallax>
            <zoom-rate>1</zoom-rate>
            <opacity>1</opacity>
            <force-own-texture>0</force-own-texture>
            <global>0</global>
            <use-render-cells>0</use-render-cells>
            <blend-mode>0</blend-mode>
            <effect-fallback>0</effect-fallback>
            <instances />
            <effects />
        </layer>
    </layers>
    <nonworld-instances />
    <effects />
</c2layout>
